{"skeleton":{"hash":"eLKZDS+CO6Qg7NerVaTQKbVO4KA","spine":"3.6.46","width":369.9,"height":317.47},"bones":[{"name":"root"},{"name":"center","parent":"root","length":282.89,"x":-7.5,"y":101.99},{"name":"body_1","parent":"center","x":-20.73,"y":5.32},{"name":"body_3","parent":"body_1","length":35.49,"rotation":-8.05,"x":27.69,"y":25.2},{"name":"body_4","parent":"body_3","x":11.94,"y":120.69},{"name":"head","parent":"body_1","length":29.44,"rotation":-129.08,"x":-27.6,"y":10.3},{"name":"feelers1","parent":"head","length":26.44,"rotation":-151.96,"x":52.74,"y":1.78},{"name":"feelers2","parent":"head","length":28.59,"rotation":-114.16,"x":59.81,"y":-24.01},{"name":"feelers3","parent":"feelers2","length":26.96,"rotation":103.17,"x":30.1,"y":0.18},{"name":"feelers4","parent":"feelers1","length":29.14,"rotation":149.27,"x":26.61,"y":0.25},{"name":"feelers5","parent":"feelers4","length":19.02,"rotation":-14.54,"x":29.14},{"name":"feelers6","parent":"feelers5","length":23.99,"rotation":-9.83,"x":19.19,"y":-0.12},{"name":"feelers7","parent":"feelers3","length":20.49,"rotation":-7.54,"x":26.96},{"name":"feelers8","parent":"feelers7","length":19.12,"rotation":-21.57,"x":20.49},{"name":"leg1","parent":"root","x":46.93,"y":20.6},{"name":"left_leg_1","parent":"body_1","length":47.93,"rotation":34.6,"x":-8.93,"y":-46.12},{"name":"left_leg_2","parent":"left_leg_1","length":81.44,"rotation":-97.3,"x":56.41,"y":-0.72},{"name":"leg2","parent":"root","x":94.17,"y":38.89},{"name":"left_leg_3","parent":"body_1","length":39.05,"rotation":38.42,"x":51.44,"y":-28.59},{"name":"left_leg_4","parent":"left_leg_3","length":77.57,"rotation":-101.92,"x":46.82,"y":0.3},{"name":"leg3","parent":"root","x":126.75,"y":63.48},{"name":"left_leg_5","parent":"body_3","length":46.63,"rotation":44.4,"x":59.01,"y":-45.56},{"name":"left_leg_6","parent":"left_leg_5","length":55.95,"rotation":-92.42,"x":53.65,"y":-1.5},{"name":"left_leg_7","parent":"left_leg_2","length":35.45,"rotation":-14.72,"x":84.05,"y":0.25,"transform":"noRotationOrReflection"},{"name":"left_leg_8","parent":"left_leg_4","length":30.98,"rotation":-18.43,"x":78.98,"y":-0.1,"transform":"noRotationOrReflection"},{"name":"left_leg_9","parent":"left_leg_6","length":31.02,"rotation":-10.57,"x":57.82,"y":-0.36,"transform":"noRotationOrReflection"},{"name":"left_lips","parent":"head","length":27.02,"rotation":1.17,"x":77.4,"y":21.27},{"name":"leg4","parent":"root","x":-125.37,"y":72.15},{"name":"right_leg_1","parent":"body_1","length":54.63,"rotation":109.36,"x":-33.05,"y":-40.7},{"name":"right_leg_2","parent":"right_leg_1","length":64.28,"rotation":118.22,"x":57.11,"y":2.22},{"name":"right_leg_3","parent":"right_leg_2","length":25.83,"rotation":-176.79,"x":64.68,"y":-1.1,"transform":"noRotationOrReflection"},{"name":"right_lips","parent":"head","length":23.73,"rotation":33.47,"x":89.42,"y":-3.29},{"name":"top","parent":"center","x":0.1,"y":278.87,"transform":"noRotationOrReflection"},{"name":"work_top","parent":"root","x":7.97,"y":472.53}],"slots":[{"name":"right_leg_3","bone":"body_1","attachment":"right_leg_3"},{"name":"right_leg_2","bone":"body_1","attachment":"right_leg_2"},{"name":"right_leg_1","bone":"right_leg_1","attachment":"right_leg_1"},{"name":"body_2","bone":"body_3","attachment":"body_2"},{"name":"body_1","bone":"body_1","attachment":"body_1"},{"name":"left_leg_3","bone":"left_leg_5","attachment":"left_leg_3"},{"name":"left_leg_2","bone":"left_leg_3","attachment":"left_leg_2"},{"name":"left_leg_1","bone":"left_leg_1","attachment":"left_leg_1"},{"name":"head","bone":"head","attachment":"head"},{"name":"right_lips","bone":"right_lips","attachment":"right_lips"},{"name":"left_lips","bone":"left_lips","attachment":"left_lips"},{"name":"thicket","bone":"body_3","attachment":"thicket"},{"name":"feelers2","bone":"feelers2","attachment":"feelers2"},{"name":"feelers1","bone":"feelers1","attachment":"feelers1"}],"ik":[{"name":"leg1","order":0,"bones":["left_leg_1","left_leg_2"],"target":"leg1","bendPositive":false},{"name":"leg2","order":1,"bones":["left_leg_3","left_leg_4"],"target":"leg2","bendPositive":false},{"name":"leg3","order":2,"bones":["left_leg_5","left_leg_6"],"target":"leg3","bendPositive":false},{"name":"leg4","order":3,"bones":["right_leg_1","right_leg_2"],"target":"leg4"}],"skins":{"default":{"body_1":{"body_1":{"x":-1.8,"y":-4.22,"width":94,"height":94}},"body_2":{"body_2":{"x":50.51,"y":-0.01,"rotation":8.05,"width":155,"height":96}},"feelers1":{"feelers1":{"type":"mesh","uvs":[1,0.25839,0.95342,0.5007,0.95109,0.62347,0.85309,0.72685,0.79242,0.61054,0.86476,0.48131,0.89976,0.25193,0.85542,0.39731,0.70842,0.66547,0.49609,0.86577,0.26509,1,0,1,0,0.84962,0.18193,0.74549,0.36542,0.60408,0.54976,0.44901,0.73642,0.21962,0.87642,0,1,0],"triangles":[13,14,9,10,11,12,10,13,9,10,12,13,8,15,7,14,15,8,9,14,8,6,17,18,16,17,6,7,16,6,15,16,7,6,18,0,5,6,1,0,1,6,2,5,1,4,5,2,3,4,2],"vertices":[1,6,18.44,-5.75,1,1,6,5.43,-4.87,1,1,6,-0.87,-5.93,1,1,6,-7.49,-0.03,1,1,6,-2.4,5.42,1,1,6,5.2,1.59,1,2,6,17.39,1.4,0.70624,9,8.52,3.72,0.29376,2,6,9.36,3.09,0.01015,9,16.28,6.37,0.98985,2,9,33.73,7.77,0.14335,10,2.49,8.67,0.85665,2,10,20.99,8.86,0.65412,11,0.24,9.15,0.34588,1,11,18.27,8.81,1,1,11,35.73,1.09,1,1,11,32.56,-6.06,1,1,11,18.39,-5.72,1,2,10,21.27,-7.68,0.00611,11,3.34,-7.1,0.99389,3,9,32.95,-8.25,0.08538,10,5.76,-7.03,0.89031,11,-12.06,-9.1,0.02431,1,9,15.1,-6.17,1,1,9,-0.13,-6.26,1,2,6,31.63,-3.17,0.25228,9,-6.06,0.38,0.74772],"hull":19}},"feelers2":{"feelers2":{"type":"mesh","uvs":[0.83094,0.1358,0.88002,0.35632,0.94083,0.62956,0.96818,0.8757,0.85293,0.8757,0.85293,0.64519,0.80018,0.43031,0.73572,0.27012,0.6693,0.42249,0.47981,0.82491,0.25321,1,0,1,0,0.74677,0.19656,0.69598,0.38409,0.51236,0.58139,0.22324,0.70642,0,0.74353,0,0.79628,0],"triangles":[10,11,12,10,13,9,10,12,13,9,14,8,13,14,9,15,16,7,7,17,18,17,7,16,8,15,7,14,15,8,7,18,0,7,0,1,1,6,7,6,1,2,5,6,2,5,2,3,4,5,3],"vertices":[2,7,25.97,-5.88,0.96433,8,-4.96,5.41,0.03567,1,7,15.6,-5.38,1,1,7,2.76,-4.76,1,1,7,-7.75,-2.09,1,1,7,-3.29,6.76,1,1,7,5.56,2.29,1,1,7,15.85,2.19,1,2,7,24.5,4.04,0.54421,8,5.03,4.58,0.45579,2,7,21.22,12.09,9.8E-4,8,13.61,5.94,0.99902,2,8,37.21,8.75,0.00118,12,9.02,10.02,0.99882,2,12,29.51,5.94,0.00647,13,6.2,8.84,0.99353,1,13,27.59,4.76,1,1,13,25.55,-5.94,1,2,12,26.62,-7.7,0.01152,13,8.53,-4.91,0.98848,2,8,34.9,-6.84,2.0E-4,12,8.77,-5.74,0.9998,1,8,13.91,-5.48,1,1,8,-0.49,-5.95,1,2,7,34.57,-1.79,0.01584,8,-2.94,-3.9,0.98416,2,7,32.52,-5.84,0.34101,8,-6.42,-0.99,0.65899],"hull":19}},"head":{"head":{"x":42.96,"y":15.82,"rotation":129.08,"width":115,"height":112}},"left_leg_1":{"left_leg_1":{"type":"mesh","uvs":[0.54039,0.13142,0.62675,0.36288,0.69972,0.55119,0.80246,0.73361,1,0.84149,1,1,0.70865,1,0.64015,0.89445,0.56868,0.75715,0.4704,0.49626,0.41084,0.26284,0.29916,0.37269,0.15324,0.47076,0,0.52569,0,0.39426,0.12048,0.3158,0.25151,0.21184,0.38255,0,0.42871,0,0.47934,0],"triangles":[6,7,3,6,3,4,6,4,5,10,17,18,10,18,19,0,10,19,10,0,1,9,10,1,9,1,2,8,9,2,8,2,3,7,8,3,16,17,10,11,16,10,15,16,11,12,15,11,14,15,12,13,14,12],"vertices":[1,16,8.14,11.87,1,1,16,34.95,11.48,1,1,16,56.94,11.49,1,2,16,80.24,15.42,0.41981,23,8.7,13,0.58019,1,23,37.75,9.21,1,1,23,42.04,-6.71,1,1,23,3.5,-17.1,1,2,16,85.04,-11.99,0.91,23,-8.42,-8.94,0.09,2,16,67.87,-14.23,0.99414,23,-21.59,2.3,0.00586,1,16,37.59,-13.9,1,2,15,44.73,-11.52,0.46938,16,12.25,-10.15,0.53062,1,15,25.65,-12.24,1,1,15,3.4,-9.28,1,1,15,-17.12,-2.06,1,1,15,-9.36,9.19,1,1,15,8.86,6.53,1,1,15,29.78,5.24,1,2,15,57.06,13.18,0.33286,16,-13.86,-1.19,0.66714,2,15,62.27,9.59,0.13025,16,-10.99,4.45,0.86975,2,15,67.98,5.65,0.01229,16,-7.84,10.63,0.98771],"hull":20}},"left_leg_2":{"left_leg_2":{"type":"mesh","uvs":[0.58458,0.11858,0.66729,0.35689,0.77185,0.63964,0.83272,0.74062,1,0.85977,1,1,0.72659,1,0.65169,0.92238,0.59082,0.75677,0.51747,0.5124,0.45661,0.30034,0.39107,0.37305,0.29431,0.44979,0.19755,0.48211,0.13201,0.46393,0,0.37507,0,0.3165,0.05085,0.2963,0.19599,0.34679,0.29119,0.24783,0.36454,0.13473,0.41916,0,0.48158,0,0.544,0],"triangles":[6,7,3,6,3,4,6,4,5,10,23,0,10,22,23,21,22,10,10,0,1,9,10,1,9,1,2,8,9,2,8,2,3,7,8,3,21,10,20,19,20,10,11,19,10,12,18,19,15,16,17,11,12,19,14,17,18,13,14,18,15,17,14,12,13,18],"vertices":[1,19,5.53,13.19,1,1,19,32.17,12.28,1,2,19,64.14,11.95,0.99221,24,-1.96,19.02,0.00779,2,19,76.92,14.63,0.45779,24,8.97,11.86,0.54221,1,24,33.79,7.48,1,1,24,38.4,-6.06,1,2,19,94.5,-9.61,0.01459,24,4.24,-17.7,0.98541,2,19,83.03,-14.99,0.9,24,-7.67,-13.39,0.1,2,19,64.33,-14.76,0.98522,24,-20.72,0.01,0.01478,1,19,37.69,-12.47,1,2,18,33.78,-11.94,0.44947,19,14.73,-10.14,0.55053,2,18,22.4,-12.38,0.97126,19,17.57,-21.18,0.02874,1,18,7.52,-10.57,1,1,18,-4.53,-5.22,1,1,18,-10.16,1.61,1,1,18,-18.18,19.54,1,1,18,-14.47,24.22,1,1,18,-7.93,21.66,1,1,18,3.88,5.72,1,1,18,20,5.82,1,2,18,34.76,8.84,0.93676,19,-5.79,-13.61,0.06324,2,18,48.95,15.13,0.21897,19,-14.95,-1.08,0.78103,2,18,55.4,10.01,0.05561,19,-11.31,6.32,0.94439,1,19,-7.68,13.71,1],"hull":24}},"left_leg_3":{"left_leg_3":{"type":"mesh","uvs":[0.63856,0.19784,0.71135,0.40409,0.79142,0.6218,0.82418,0.71576,1,0.81659,1,1,0.76109,1,0.65918,0.94493,0.60337,0.77993,0.53907,0.55763,0.47846,0.33316,0.4081,0.46837,0.2989,0.61045,0.19214,0.66087,0.0696,0.61274,0,0.54399,0,0.4592,0.03199,0.40649,0.09872,0.43857,0.17758,0.46607,0.26736,0.3492,0.35229,0.21628,0.46148,0,0.51486,0,0.57719,0],"triangles":[6,7,3,6,3,4,6,4,5,7,8,3,10,22,23,10,23,24,24,0,10,10,0,1,9,10,1,9,1,2,8,9,2,8,2,3,22,10,21,20,21,10,11,20,10,12,19,20,18,15,16,18,16,17,11,12,20,14,15,18,14,18,19,13,14,19,12,13,19],"vertices":[1,22,12.1,11.65,1,1,22,29.95,11.63,1,2,22,49.03,11.98,0.68,25,2.63,14.92,0.32,2,22,57.13,11.93,0.19,25,8.27,9.11,0.81,1,25,33.12,6.44,1,1,25,35.59,-6.53,1,2,22,69.38,-6.57,6.4E-4,25,3.67,-12.6,0.99936,2,22,58.39,-15.9,0.74,25,-10.69,-11.3,0.26,2,22,44.29,-15.61,0.90121,25,-20.36,-1.05,0.09879,2,21,38.48,-26.96,0.00695,22,26.13,-13.99,0.99305,2,21,41.43,-9.06,0.63001,22,8.11,-11.87,0.36999,2,21,27.95,-11.22,0.99977,22,10.89,-25.23,2.3E-4,1,21,9.92,-10.66,1,1,21,-3.92,-4.98,1,1,21,-15.29,7.69,1,1,21,-19.98,17.29,1,1,21,-16.36,22.2,1,1,21,-10.61,22.68,1,1,21,-4.67,15.44,1,1,21,2.8,7.49,1,1,21,17.62,7.03,1,1,21,32.59,7.89,1,2,21,53.78,11.63,0.47286,22,-13.12,-0.47,0.52714,2,21,59.63,7.33,0.13977,22,-9.09,5.57,0.86023,2,21,66.46,2.3,5.7E-4,22,-4.38,12.62,0.99943],"hull":25}},"left_lips":{"left_lips":{"x":10.9,"y":2,"rotation":127.91,"width":32,"height":32}},"right_leg_1":{"right_leg_1":{"type":"mesh","uvs":[0.81603,0.06939,0.8312,0.31798,0.88431,0.57377,0.95511,0.78994,1,1,0.90454,1,0.8312,0.90162,0.74522,0.72149,0.69464,0.46209,0.5859,0.71428,0.42153,0.94485,0.2698,1,0,1,0,0.72149,0.31532,0.62781,0.46452,0.40444,0.6036,0.13784,0.70223,0,0.75281,0],"triangles":[14,11,13,13,11,12,14,10,11,10,14,9,14,15,9,9,15,8,15,16,8,0,8,18,8,16,17,8,17,18,5,3,4,5,6,3,6,7,3,7,2,3,2,7,8,8,1,2,1,8,0],"vertices":[2,28,61.67,-10.34,0.57459,29,-13.22,2,0.42541,1,28,44.03,-5.82,1,1,28,24.58,-4.84,1,1,28,7.25,-6.56,1,1,28,-8.76,-5.88,1,1,28,-5.47,3.49,1,1,28,3.83,8.3,1,2,28,19.2,12.38,0.99958,29,27.05,28.44,4.2E-4,2,28,38.81,11.07,0.5242,29,16.52,11.84,0.4758,2,28,25.19,27.84,2.6E-4,29,37.76,15.79,0.99974,1,29,61.71,14.38,1,2,29,75.27,5.37,0.59299,30,2.99,12.04,0.40701,1,30,31.01,10.42,1,1,30,29.83,-9.87,1,2,29,51.93,-9.33,0.67027,30,-3.3,-14.81,0.32973,1,29,29.43,-8.74,1,1,29,5.29,-11.05,1,2,28,70.37,-0.86,0.10555,29,-9.05,-10.18,0.89445,2,28,68.63,-5.82,0.23587,29,-12.57,-6.27,0.76413],"hull":19}},"right_leg_2":{"right_leg_2":{"type":"mesh","uvs":[0.72819,0.24213,0.80668,0.52886,0.8987,0.70995,1,0.83445,1,1,0.77149,0.87595,0.64158,0.67222,0.58204,0.43831,0.48189,0.71372,0.35739,1,0.22207,1,0,1,0,0.72504,0.18688,0.69863,0.33845,0.40813,0.49001,0.11763,0.56038,0,0.61993,0,0.70112,0],"triangles":[7,17,18,7,15,16,16,17,7,18,0,7,14,15,7,7,0,1,6,7,1,6,1,2,8,14,7,13,14,8,5,6,2,5,2,3,10,11,12,9,10,13,10,12,13,8,9,13,5,3,4],"vertices":[10.15,21.55,17.37,2.62,25.83,-9.33,35.15,-17.55,35.15,-28.47,14.13,-20.29,2.18,-6.84,-3.3,8.6,-12.51,-9.58,-23.97,-28.47,-36.42,-28.47,-56.85,-28.47,-56.85,-10.33,-39.65,-8.58,-25.71,10.59,-11.77,29.76,-5.29,37.53,0.19,37.53,7.66,37.53],"hull":19}},"right_leg_3":{"right_leg_3":{"x":21.1,"y":6.23,"width":60,"height":61}},"right_lips":{"right_lips":{"x":12.64,"y":1.58,"rotation":95.61,"width":26,"height":35}},"thicket":{"thicket":{"type":"mesh","uvs":[0.7851,0.08333,1,0.32835,1,0.71857,0.84137,0.95225,0.54124,1,0.44574,1,0.29056,0.86604,0.08422,0.87511,0,0.71857,0,0.51665,0.05011,0.25121,0.21212,0.0924,0.32808,0,0.59922,0,0.18142,0.30339,0.30932,0.47582,0.4969,0.50758,0.71006,0.44859,0.8516,0.34423,0.25816,0.13778,0.48837,0.08787,0.74076,0.16727,0.48837,0.28071,0.49349,0.71857,0.78339,0.65278,0.94198,0.49397,0.26157,0.62782,0.08934,0.44632],"triangles":[20,12,13,19,11,12,19,12,20,21,13,0,20,13,21,22,20,21,19,20,22,14,10,11,14,11,19,14,19,22,18,21,0,1,18,0,22,21,18,27,10,14,17,22,18,15,14,22,27,14,15,25,18,1,17,18,25,16,22,17,15,22,16,9,10,27,26,27,15,24,17,25,26,8,9,26,9,27,16,26,15,23,26,16,24,23,16,24,16,17,25,1,2,24,25,2,6,26,23,7,8,26,6,7,26,3,24,2,23,24,3,3,4,23,5,6,23,4,5,23],"vertices":[2,3,90.94,181.53,0.95,4,79,60.84,0.05,2,3,162.99,135.54,0.95,4,151.05,14.85,0.05,1,3,175.39,47.84,1,1,3,135.39,-11.39,1,1,3,47.16,-34.82,1,1,3,18.6,-38.86,1,1,3,-32.06,-15.31,1,1,3,-93.47,-26.07,1,1,3,-123.63,5.55,1,1,3,-130.05,50.93,1,2,3,-123.5,112.71,0.95,4,-135.44,-7.97,0.05,2,3,-80.11,155.26,0.95,4,-92.05,34.57,0.05,2,3,-48.37,180.93,0.95,4,-60.31,60.24,0.05,2,3,32.71,192.4,0.95,4,20.77,71.71,0.05,2,3,-82.58,106.54,0.9,4,-94.52,-14.15,0.1,2,3,-38.85,73.19,0.9,4,-50.8,-47.5,0.1,2,3,18.25,73.98,0.9,4,6.31,-46.7,0.1,2,3,80.11,96.26,0.9,4,68.17,-24.43,0.1,2,3,119.12,125.7,0.9,4,107.18,5.01,0.1,2,3,-64.9,147.01,0.9,4,-76.84,26.32,0.1,2,3,2.36,167.96,0.9,4,-9.58,47.27,0.1,2,3,80.35,160.79,0.9,4,68.41,40.1,0.1,2,3,8.49,124.62,0.8,4,-3.45,3.93,0.2,2,3,23.93,26.42,0.95,4,11.99,-94.27,0.05,2,3,108.53,53.46,0.95,4,96.59,-67.22,0.05,2,3,150.91,95.87,0.95,4,138.96,-24.82,0.05,2,3,-48.3,37.01,0.95,4,-60.24,-83.68,0.05,2,3,-105.57,70.52,0.95,4,-117.51,-50.17,0.05],"hull":14}}}},"events":{"impact":{}},"animations":{"attack1":{"bones":{"feelers3":{"rotate":[{"time":0,"angle":4.42,"curve":"stepped"},{"time":0.3333,"angle":4.42,"curve":[0.384,0.01,0.702,0.47]},{"time":0.4333,"angle":-19.87,"curve":[0.332,0.47,0.636,1]},{"time":0.5333,"angle":12.82,"curve":[0.384,0.01,0.702,0.47]},{"time":1,"angle":4.42}]},"feelers4":{"rotate":[{"time":0,"angle":4.42,"curve":"stepped"},{"time":0.3333,"angle":4.42,"curve":[0.408,0.01,0.653,1]},{"time":0.4333,"angle":-12.76,"curve":[0.333,0.46,0.636,1]},{"time":0.5333,"angle":12.82,"curve":[0.408,0.01,0.653,1]},{"time":1,"angle":4.42}]},"feelers8":{"rotate":[{"time":0,"angle":-4.35,"curve":"stepped"},{"time":0.3333,"angle":-4.35,"curve":[0.348,0.31,0.674,0.68]},{"time":0.4333,"angle":-28.64,"curve":[0.32,0.56,0.64,1]},{"time":0.5333,"angle":4.05,"curve":[0.348,0.31,0.674,0.68]},{"time":1,"angle":-4.35}]},"right_leg_2":{"rotate":[{"time":0,"angle":0.34}]},"feelers5":{"rotate":[{"time":0,"angle":1.32,"curve":"stepped"},{"time":0.3333,"angle":1.32,"curve":[0.319,0.57,0.642,1]},{"time":0.4333,"angle":-9.7,"curve":[0.32,0.62,0.65,1]},{"time":0.5333,"angle":9.71,"curve":[0.319,0.57,0.642,1]},{"time":1,"angle":1.32}]},"left_leg_1":{"rotate":[{"time":0,"angle":0.36}]},"left_leg_6":{"rotate":[{"time":0,"angle":-0.19}]},"left_leg_2":{"rotate":[{"time":0,"angle":-0.29}]},"body_4":{"rotate":[{"time":0,"angle":-17.77,"curve":[0.25,0,0.75,1]},{"time":0.5,"angle":-43.33,"curve":[0.25,0,0.255,1]},{"time":0.6333,"angle":27.83,"curve":[0.25,0,0.75,1]},{"time":1,"angle":-17.77}],"translate":[{"time":0,"x":2.4,"y":-4.82,"curve":[0.25,0,0.75,1]},{"time":0.4,"x":115.49,"y":37.37,"curve":[0.25,0,0.255,1]},{"time":0.6,"x":-146.98,"y":-110.24,"curve":[0.25,0,0.75,1]},{"time":1,"x":2.4,"y":-4.82}]},"left_lips":{"rotate":[{"time":0.3,"angle":0,"curve":[0.25,0,0.75,1]},{"time":0.4,"angle":53.04,"curve":[0.25,0,0.75,1]},{"time":0.4667,"angle":-19.23,"curve":[0.25,0,0.75,1]},{"time":0.5667,"angle":0}]},"head":{"rotate":[{"time":0,"angle":1.51,"curve":[0.324,0.34,0.652,0.69]},{"time":0.3333,"angle":9.8,"curve":[0.449,0,0.75,1]},{"time":0.5333,"angle":-14.51,"curve":[0.294,0.6,0.619,1]},{"time":1,"angle":1.51}],"scale":[{"time":0.3333,"x":1,"y":1,"curve":[0.25,0,0.75,1]},{"time":0.4,"x":0.721,"y":1.326,"curve":[0.25,0,0.75,1]},{"time":0.4667,"x":1.242,"y":0.77,"curve":[0.25,0,0.75,1]},{"time":0.5333,"x":1,"y":1}]},"right_leg_1":{"rotate":[{"time":0,"angle":-0.1}]},"center":{"rotate":[{"time":0,"angle":-0.02,"curve":"stepped"},{"time":0.2667,"angle":-0.02,"curve":[0.25,0,0.75,1]},{"time":0.3832,"angle":-13.69,"curve":[0.25,0,0.75,1]},{"time":0.5333,"angle":6.21,"curve":[0.25,0,0.75,1]},{"time":1,"angle":-0.02}],"translate":[{"time":0,"x":0,"y":0,"curve":[0.25,0,0.75,1]},{"time":0.33,"x":52.22,"y":17.09,"curve":[0.25,0,0.75,1]},{"time":0.4577,"x":-30.79,"y":-32.04,"curve":[0.449,0.01,0.75,1]},{"time":1,"x":0,"y":0}]},"left_leg_5":{"rotate":[{"time":0,"angle":0.21}]},"feelers7":{"rotate":[{"time":0,"angle":1.32,"curve":"stepped"},{"time":0.3333,"angle":1.32,"curve":[0.329,0.39,0.661,0.73]},{"time":0.4333,"angle":-22.98,"curve":[0.32,0.62,0.65,1]},{"time":0.5333,"angle":9.71,"curve":[0.329,0.39,0.661,0.73]},{"time":1,"angle":1.32}]},"left_leg_4":{"rotate":[{"time":0,"angle":-0.34}]},"feelers6":{"rotate":[{"time":0,"angle":-4.35,"curve":"stepped"},{"time":0.3333,"angle":-4.35,"curve":[0.344,0.4,0.637,1]},{"time":0.4333,"angle":-15.83,"curve":[0.32,0.55,0.64,1]},{"time":0.5333,"angle":4.05,"curve":[0.344,0.4,0.637,1]},{"time":1,"angle":-4.35}]},"right_lips":{"rotate":[{"time":0.3,"angle":0,"curve":[0.25,0,0.75,1]},{"time":0.4,"angle":-45.54,"curve":[0.25,0,0.75,1]},{"time":0.4667,"angle":33.97,"curve":[0.25,0,0.75,1]},{"time":0.5667,"angle":0}]},"left_leg_3":{"rotate":[{"time":0,"angle":0.38}]}},"events":[{"time":0.4667,"name":"impact"}]},"hit":{"bones":{"left_leg_5":{"rotate":[{"time":0,"angle":0.21}]},"body_4":{"rotate":[{"time":0,"angle":-17.77,"curve":[0.25,0,0.75,1]},{"time":0.0811,"angle":15.5,"curve":[0.954,0,0.75,1]},{"time":0.4,"angle":-17.77}],"translate":[{"time":0,"x":2.4,"y":-4.82,"curve":[0.25,0,0.75,1]},{"time":0.0811,"x":31.61,"y":-61.86,"curve":[0.954,0,0.75,1]},{"time":0.4,"x":2.4,"y":-4.82}]},"feelers6":{"rotate":[{"time":0,"angle":-4.35,"curve":[0.25,0,0.199,1]},{"time":0.1892,"angle":-22.48,"curve":[0.709,0,0.75,1]},{"time":0.4,"angle":-4.35}]},"right_leg_2":{"rotate":[{"time":0,"angle":0.34}]},"left_leg_2":{"rotate":[{"time":0,"angle":-0.29}]},"feelers3":{"rotate":[{"time":0,"angle":4.42,"curve":[0.25,0,0.199,1]},{"time":0.1622,"angle":-45.26,"curve":[0.709,0,0.75,1]},{"time":0.4,"angle":4.42}]},"feelers8":{"rotate":[{"time":0,"angle":-4.35,"curve":[0.25,0,0.199,1]},{"time":0.1892,"angle":-22.48,"curve":[0.709,0,0.75,1]},{"time":0.4,"angle":-4.35}]},"right_lips":{"rotate":[{"time":0,"angle":0,"curve":[0.25,0,0.199,1]},{"time":0.1351,"angle":-67.83,"curve":[0.709,0,0.75,1]},{"time":0.4,"angle":0}]},"right_leg_1":{"rotate":[{"time":0,"angle":-0.1}]},"feelers7":{"rotate":[{"time":0,"angle":1.32,"curve":[0.25,0,0.199,1]},{"time":0.1892,"angle":-16.82,"curve":[0.709,0,0.75,1]},{"time":0.4,"angle":1.32}]},"center":{"rotate":[{"time":0,"angle":-0.02,"curve":[0.648,-1.37,0.199,1]},{"time":0.1622,"angle":6.64,"curve":[0.709,0,0.75,1]},{"time":0.4,"angle":-0.02}],"translate":[{"time":0,"x":0,"y":0,"curve":[0.25,0,0.199,1]},{"time":0.1081,"x":24.01,"y":-37.4,"curve":[0.709,0,0.75,1]},{"time":0.4,"x":0,"y":0}]},"left_leg_1":{"rotate":[{"time":0,"angle":0.36}]},"head":{"rotate":[{"time":0,"angle":1.51,"curve":[0.435,0,0.645,0.47]},{"time":0.0811,"angle":-12.37,"curve":[0.154,0.46,0.393,1]},{"time":0.1892,"angle":33.37,"curve":[0.709,0,0.75,1]},{"time":0.4,"angle":1.51}]},"feelers4":{"rotate":[{"time":0,"angle":4.42,"curve":[0.25,0,0.199,1]},{"time":0.1622,"angle":-45.26,"curve":[0.709,0,0.75,1]},{"time":0.4,"angle":4.42}]},"left_leg_3":{"rotate":[{"time":0,"angle":0.38}]},"left_leg_4":{"rotate":[{"time":0,"angle":-0.34}]},"left_leg_6":{"rotate":[{"time":0,"angle":-0.19}]},"feelers5":{"rotate":[{"time":0,"angle":1.32,"curve":[0.25,0,0.199,1]},{"time":0.1892,"angle":-16.82,"curve":[0.709,0,0.75,1]},{"time":0.4,"angle":1.32}]},"left_lips":{"rotate":[{"time":0,"angle":0,"curve":[0.25,0,0.199,1]},{"time":0.1351,"angle":36.43,"curve":[0.709,0,0.75,1]},{"time":0.4,"angle":0}]}}},"idle":{"bones":{"center":{"rotate":[{"time":0,"angle":-0.02,"curve":[0.372,0.48,0.752,1]},{"time":0.2667,"angle":-2.87,"curve":[0.25,0,0.75,1]},{"time":0.7667,"angle":2.36,"curve":[0.252,0,0.622,0.48]},{"time":1,"angle":-0.02}],"translate":[{"time":0,"x":0,"y":0,"curve":[0.342,0,0.622,0.99]},{"time":0.5,"x":6.27,"y":12.65,"curve":[0.342,0,0.622,0.99]},{"time":1,"x":0,"y":0}]},"left_leg_1":{"rotate":[{"time":0,"angle":0.36}]},"left_leg_2":{"rotate":[{"time":0,"angle":-0.29}]},"left_leg_3":{"rotate":[{"time":0,"angle":0.38}]},"left_leg_4":{"rotate":[{"time":0,"angle":-0.34}]},"left_leg_5":{"rotate":[{"time":0,"angle":0.21}]},"left_leg_6":{"rotate":[{"time":0,"angle":-0.19}]},"head":{"rotate":[{"time":0,"angle":1.51,"curve":[0.282,0.48,0.574,1]},{"time":0.2667,"angle":7.5,"curve":[0.25,0,0.75,1]},{"time":0.7667,"angle":-2.52,"curve":[0.392,0,0.691,0.48]},{"time":1,"angle":1.51}]},"feelers4":{"rotate":[{"time":0,"angle":4.42,"curve":[0.408,0.01,0.653,1]},{"time":0.5,"angle":-6.87,"curve":[0.408,0.01,0.653,1]},{"time":1,"angle":4.42}]},"feelers5":{"rotate":[{"time":0,"angle":1.32,"curve":[0.319,0.57,0.642,1]},{"time":0.1667,"angle":4.42,"curve":[0.402,0.01,0.543,0.98]},{"time":0.6667,"angle":-6.87,"curve":[0.402,0.01,0.696,0.6]},{"time":1,"angle":1.32}]},"feelers6":{"rotate":[{"time":0,"angle":-4.35,"curve":[0.344,0.4,0.637,1]},{"time":0.3333,"angle":4.42,"curve":[0.374,0.01,0.543,0.98]},{"time":0.8333,"angle":-6.87,"curve":[0.374,0.01,0.699,0.44]},{"time":1,"angle":-4.35}]},"feelers3":{"rotate":[{"time":0,"angle":4.42,"curve":[0.408,0.01,0.653,1]},{"time":0.5,"angle":-6.87,"curve":[0.408,0.01,0.653,1]},{"time":1,"angle":4.42}]},"feelers7":{"rotate":[{"time":0,"angle":1.32,"curve":[0.319,0.57,0.642,1]},{"time":0.1667,"angle":4.42,"curve":[0.408,0.01,0.653,1]},{"time":0.6667,"angle":-6.87,"curve":[0.402,0.01,0.696,0.6]},{"time":1,"angle":1.32}]},"feelers8":{"rotate":[{"time":0,"angle":-4.35,"curve":[0.344,0.4,0.637,1]},{"time":0.3333,"angle":4.42,"curve":[0.408,0.01,0.653,1]},{"time":0.8333,"angle":-6.87,"curve":[0.374,0.01,0.699,0.44]},{"time":1,"angle":-4.35}]},"left_lips":{"rotate":[{"time":0,"angle":0,"curve":[0.25,0,0.75,1]},{"time":0.1333,"angle":-12.09,"curve":[0.25,0,0.75,1]},{"time":0.2667,"angle":0,"curve":[0.25,0,0.75,1]},{"time":0.3667,"angle":-12.09,"curve":[0.25,0,0.75,1]},{"time":0.5,"angle":0}]},"right_lips":{"rotate":[{"time":0,"angle":0},{"time":0.1333,"angle":10.24},{"time":0.2667,"angle":0},{"time":0.3667,"angle":10.24},{"time":0.5,"angle":0}]},"body_4":{"rotate":[{"time":0,"angle":-17.77,"curve":[0.25,0,0.75,1]},{"time":0.5,"angle":33.77,"curve":[0.25,0,0.75,1]},{"time":1,"angle":-17.77}],"translate":[{"time":0,"x":2.4,"y":-4.82,"curve":[0.306,0.48,0.608,0.99]},{"time":0.2667,"x":-61.61,"y":-39.59,"curve":[0.383,0,0.643,1]},{"time":0.7667,"x":28.27,"y":5.96,"curve":[0.381,0,0.702,0.62]},{"time":1,"x":2.4,"y":-4.82}]},"right_leg_1":{"rotate":[{"time":0,"angle":-0.1}]},"right_leg_2":{"rotate":[{"time":0,"angle":0.34}]}}},"run":{"bones":{"center":{"rotate":[{"time":0,"angle":1.19,"curve":[0.363,0.44,0.755,1]},{"time":0.1667,"angle":-4.65,"curve":[0.25,0,0.75,1]},{"time":0.5,"angle":4.58,"curve":[0.46,0,0.744,0.57]},{"time":0.6667,"angle":1.19,"curve":[0.363,0.44,0.755,1]},{"time":0.8333,"angle":-4.65,"curve":[0.25,0,0.75,1]},{"time":1.1667,"angle":4.58,"curve":[0.46,0,0.744,0.57]},{"time":1.3333,"angle":1.19}],"translate":[{"time":0,"x":-3.87,"y":0,"curve":[0.25,0,0.75,1]},{"time":0.3333,"x":8.02,"y":0,"curve":[0.148,0,0.579,1]},{"time":0.6667,"x":-3.87,"y":0,"curve":[0.25,0,0.75,1]},{"time":1,"x":8.02,"y":0,"curve":[0.148,0,0.579,1]},{"time":1.3333,"x":-3.87,"y":0}]},"left_leg_7":{"rotate":[{"time":0,"angle":0},{"time":0.1,"angle":-16.62},{"time":0.2333,"angle":14.31},{"time":0.3333,"angle":0,"curve":"stepped"},{"time":0.6667,"angle":0},{"time":0.7667,"angle":-16.62},{"time":0.9,"angle":14.31},{"time":1,"angle":0}]},"leg1":{"translate":[{"time":0,"x":-20,"y":-14,"curve":[0.245,0,0.637,0.56]},{"time":0.1667,"x":-33.75,"y":1.09,"curve":[0.25,0,0.75,1]},{"time":0.3333,"x":-54.59,"y":-28.16,"curve":[0.25,0,0.75,1]},{"time":0.6667,"x":-20,"y":-14,"curve":[0.245,0,0.637,0.56]},{"time":0.8333,"x":-33.75,"y":1.09,"curve":[0.25,0,0.75,1]},{"time":1,"x":-54.59,"y":-28.16,"curve":[0.25,0,0.75,1]},{"time":1.3333,"x":-20,"y":-14}]},"right_leg_3":{"rotate":[{"time":0.3333,"angle":0},{"time":0.4333,"angle":17.53},{"time":0.5667,"angle":336.08},{"time":0.6667,"angle":0,"curve":"stepped"},{"time":1,"angle":0},{"time":1.1,"angle":17.53},{"time":1.2333,"angle":336.08},{"time":1.3333,"angle":0}]},"left_leg_9":{"rotate":[{"time":0,"angle":0},{"time":0.1,"angle":-16.62},{"time":0.2333,"angle":14.31},{"time":0.3333,"angle":0,"curve":"stepped"},{"time":0.6667,"angle":0},{"time":0.7667,"angle":-16.62},{"time":0.9,"angle":14.31},{"time":1,"angle":0}]},"left_leg_8":{"rotate":[{"time":0.3333,"angle":0},{"time":0.4333,"angle":-16.62},{"time":0.5667,"angle":14.31},{"time":0.6667,"angle":0,"curve":"stepped"},{"time":1,"angle":0},{"time":1.1,"angle":-16.62},{"time":1.2333,"angle":14.31},{"time":1.3333,"angle":0}]},"right_leg_2":{"rotate":[{"time":0,"angle":0.34}]},"right_leg_1":{"rotate":[{"time":0,"angle":-0.1}]},"leg4":{"translate":[{"time":0,"x":-42,"y":-41,"curve":[0.25,0,0.75,1]},{"time":0.3333,"x":24,"y":7,"curve":[0.25,0,0.625,0.5]},{"time":0.5,"x":-12,"y":22,"curve":[0.375,0.5,0.75,1]},{"time":0.6667,"x":-42,"y":-41,"curve":[0.25,0,0.75,1]},{"time":1,"x":24,"y":7,"curve":[0.25,0,0.625,0.5]},{"time":1.1667,"x":-12,"y":22,"curve":[0.375,0.5,0.75,1]},{"time":1.3333,"x":-42,"y":-41}]},"body_4":{"rotate":[{"time":0,"angle":-24.08,"curve":[0.25,0,0.625,0.5]},{"time":0.1667,"angle":-4.19,"curve":[0.375,0.5,0.75,1]},{"time":0.3333,"angle":15.7,"curve":[0.25,0,0.75,1]},{"time":0.6667,"angle":-24.08,"curve":[0.25,0,0.75,1]},{"time":1,"angle":15.7,"curve":[0.25,0,0.75,1]},{"time":1.3333,"angle":-24.08}],"translate":[{"time":0,"x":1.61,"y":-7.9,"curve":[0.375,0.5,0.75,1]},{"time":0.1667,"x":-32.79,"y":-8.79,"curve":[0.25,0,0.625,0.5]},{"time":0.5,"x":36,"y":-7.01,"curve":[0.25,0,0.75,1]},{"time":0.8333,"x":-32.79,"y":-8.79,"curve":[0.25,0,0.75,1]},{"time":1.1667,"x":36,"y":-7.01,"curve":[0.25,0,0.625,0.5]},{"time":1.3333,"x":1.61,"y":-7.9}]},"right_lips":{"rotate":[{"time":0,"angle":0,"curve":[0.25,0,0.75,1]},{"time":0.3333,"angle":-23.33,"curve":[0.25,0,0.75,1]},{"time":0.6667,"angle":0,"curve":[0.25,0,0.75,1]},{"time":1,"angle":-23.33,"curve":[0.25,0,0.75,1]},{"time":1.3333,"angle":0}]},"left_lips":{"rotate":[{"time":0,"angle":0,"curve":[0.25,0,0.75,1]},{"time":0.3333,"angle":21.07,"curve":[0.25,0,0.75,1]},{"time":0.6667,"angle":0,"curve":[0.25,0,0.75,1]},{"time":1,"angle":21.07,"curve":[0.25,0,0.75,1]},{"time":1.3333,"angle":0}]},"feelers8":{"rotate":[{"time":0,"angle":-3.89,"curve":[0.289,0.17,0.755,1]},{"time":0.3,"angle":2.24,"curve":[0.25,0,0.75,1]},{"time":0.6333,"angle":-4.16,"curve":[0.305,0,0.64,0.36]},{"time":0.6667,"angle":-3.89,"curve":[0.289,0.17,0.755,1]},{"time":0.9667,"angle":2.24,"curve":[0.25,0,0.75,1]},{"time":1.3,"angle":-4.16,"curve":[0.305,0,0.64,0.36]},{"time":1.3333,"angle":-3.89}]},"feelers7":{"rotate":[{"time":0,"angle":-1.81,"curve":[0.363,0.44,0.755,1]},{"time":0.2,"angle":2.24,"curve":[0.25,0,0.75,1]},{"time":0.5333,"angle":-4.16,"curve":[0.258,0,0.619,0.45]},{"time":0.6667,"angle":-1.81,"curve":[0.363,0.44,0.755,1]},{"time":0.8667,"angle":2.24,"curve":[0.25,0,0.75,1]},{"time":1.2,"angle":-4.16,"curve":[0.258,0,0.619,0.45]},{"time":1.3333,"angle":-1.81}]},"feelers3":{"rotate":[{"time":0,"angle":0.69,"curve":[0.382,0.58,0.731,1]},{"time":0.1,"angle":2.24,"curve":[0.25,0,0.75,1]},{"time":0.4333,"angle":-4.16,"curve":[0.243,0,0.655,0.63]},{"time":0.6667,"angle":0.69,"curve":[0.382,0.58,0.731,1]},{"time":0.7667,"angle":2.24,"curve":[0.25,0,0.75,1]},{"time":1.1,"angle":-4.16,"curve":[0.243,0,0.655,0.63]},{"time":1.3333,"angle":0.69}]},"feelers6":{"rotate":[{"time":0,"angle":-7.14,"curve":[0.289,0.17,0.755,1]},{"time":0.3,"angle":1.79},{"time":0.6333,"angle":-7.54,"curve":[0.305,0,0.64,0.36]},{"time":0.6667,"angle":-7.14,"curve":[0.289,0.17,0.755,1]},{"time":0.9667,"angle":1.79},{"time":1.3,"angle":-7.54,"curve":[0.305,0,0.64,0.36]},{"time":1.3333,"angle":-7.14}]},"feelers5":{"rotate":[{"time":0,"angle":-4.11,"curve":[0.363,0.44,0.755,1]},{"time":0.2,"angle":1.79},{"time":0.5333,"angle":-7.54,"curve":[0.258,0,0.619,0.45]},{"time":0.6667,"angle":-4.11,"curve":[0.363,0.44,0.755,1]},{"time":0.8667,"angle":1.79},{"time":1.2,"angle":-7.54,"curve":[0.258,0,0.619,0.45]},{"time":1.3333,"angle":-4.11}]},"feelers4":{"rotate":[{"time":0,"angle":-0.47,"curve":[0.382,0.58,0.731,1]},{"time":0.1,"angle":1.79},{"time":0.4333,"angle":-7.54,"curve":[0.243,0,0.655,0.63]},{"time":0.6667,"angle":-0.47,"curve":[0.382,0.58,0.731,1]},{"time":0.7667,"angle":1.79},{"time":1.1,"angle":-7.54,"curve":[0.243,0,0.655,0.63]},{"time":1.3333,"angle":-0.47}]},"feelers1":{"rotate":[{"time":0,"angle":1.79,"curve":[0.25,0,0.75,1]},{"time":0.3333,"angle":-7.54,"curve":[0.25,0,0.75,1]},{"time":0.6667,"angle":1.79,"curve":[0.25,0,0.75,1]},{"time":1,"angle":-7.54,"curve":[0.25,0,0.75,1]},{"time":1.3333,"angle":1.79}]},"feelers2":{"rotate":[{"time":0,"angle":2.24,"curve":[0.25,0,0.75,1]},{"time":0.3333,"angle":-4.16,"curve":[0.25,0,0.75,1]},{"time":0.6667,"angle":2.24,"curve":[0.25,0,0.75,1]},{"time":1,"angle":-4.16,"curve":[0.25,0,0.75,1]},{"time":1.3333,"angle":2.24}]},"head":{"rotate":[{"time":0,"angle":0,"curve":[0.256,0.35,0.75,1]},{"time":0.1667,"angle":4.59,"curve":[0.25,0,0.75,1]},{"time":0.5,"angle":-6.3,"curve":[0.377,0,0.623,0.45]},{"time":0.6667,"angle":0,"curve":[0.256,0.35,0.75,1]},{"time":0.8333,"angle":4.59,"curve":[0.25,0,0.75,1]},{"time":1.1667,"angle":-6.3,"curve":[0.377,0,0.623,0.45]},{"time":1.3333,"angle":0}]},"left_leg_6":{"rotate":[{"time":0,"angle":-0.19}]},"left_leg_5":{"rotate":[{"time":0,"angle":0.21}]},"leg3":{"translate":[{"time":0,"x":11.6,"y":-7.63},{"time":0.1667,"x":-15.09,"y":-1.8},{"time":0.3333,"x":-12,"y":-26},{"time":0.6667,"x":11.6,"y":-7.63},{"time":0.8333,"x":-15.09,"y":-1.8},{"time":1,"x":-12,"y":-26},{"time":1.3333,"x":11.6,"y":-7.63}]},"left_leg_4":{"rotate":[{"time":0,"angle":-0.34}]},"left_leg_3":{"rotate":[{"time":0,"angle":0.38}]},"leg2":{"translate":[{"time":0,"x":-53,"y":-29,"curve":[0.25,0,0.75,1]},{"time":0.3333,"x":5,"y":-10,"curve":[0.25,0,0.625,0.5]},{"time":0.5,"x":-33,"y":5,"curve":[0.375,0.5,0.75,1]},{"time":0.6667,"x":-53,"y":-29,"curve":[0.25,0,0.75,1]},{"time":1,"x":5,"y":-10,"curve":[0.25,0,0.625,0.5]},{"time":1.1667,"x":-33,"y":5,"curve":[0.375,0.5,0.75,1]},{"time":1.3333,"x":-53,"y":-29}]},"left_leg_2":{"rotate":[{"time":0,"angle":-0.29}]},"left_leg_1":{"rotate":[{"time":0,"angle":0.36}]}}},"stun":{"bones":{"center":{"rotate":[{"time":0,"angle":-0.02,"curve":[0.372,0.48,0.752,1]},{"time":0.3667,"angle":-2.87,"curve":[0.25,0,0.75,1]},{"time":1.0333,"angle":2.36,"curve":[0.252,0,0.622,0.48]},{"time":1.3333,"angle":-0.02}],"translate":[{"time":0,"x":0,"y":0,"curve":[0.342,0,0.622,0.99]},{"time":0.6667,"x":18.1,"y":-3.4,"curve":[0.342,0,0.622,0.99]},{"time":1.3333,"x":0,"y":0}]},"left_leg_1":{"rotate":[{"time":0,"angle":0.36}]},"left_leg_2":{"rotate":[{"time":0,"angle":-0.29}]},"leg2":{"translate":[{"time":0,"x":-28.99,"y":0}]},"left_leg_3":{"rotate":[{"time":0,"angle":0.38}]},"left_leg_4":{"rotate":[{"time":0,"angle":-0.34}]},"leg3":{"translate":[{"time":0,"x":-28.99,"y":0}]},"left_leg_5":{"rotate":[{"time":0,"angle":0.21}]},"left_leg_6":{"rotate":[{"time":0,"angle":-0.19}]},"head":{"rotate":[{"time":0,"angle":36.58,"curve":[0.282,0.48,0.574,1]},{"time":0.3667,"angle":42.57,"curve":[0.25,0,0.75,1]},{"time":1.0333,"angle":32.55,"curve":[0.392,0,0.691,0.48]},{"time":1.3333,"angle":36.58}]},"feelers4":{"rotate":[{"time":0,"angle":7.55,"curve":[0.408,0.01,0.653,1]},{"time":0.6667,"angle":18.84,"curve":[0.408,0.01,0.653,1]},{"time":1.3333,"angle":7.55}]},"feelers5":{"rotate":[{"time":0,"angle":10.19,"curve":[0.276,0.55,0.588,0.98]},{"time":0.2333,"angle":-0.17,"curve":[0.402,0.01,0.653,1]},{"time":0.9,"angle":23.49,"curve":[0.427,0.01,0.674,0.59]},{"time":1.3333,"angle":10.19}]},"feelers6":{"rotate":[{"time":0,"angle":15.72,"curve":[0.288,0.4,0.55,0.99]},{"time":0.4667,"angle":-3.7,"curve":[0.374,0.01,0.653,1]},{"time":1.1,"angle":18.84,"curve":[0.385,0.01,0.699,0.44]},{"time":1.3333,"angle":15.72}]},"feelers3":{"rotate":[{"time":0,"angle":7.55,"curve":[0.408,0.01,0.653,1]},{"time":0.6667,"angle":18.84,"curve":[0.408,0.01,0.653,1]},{"time":1.3333,"angle":7.55}]},"feelers7":{"rotate":[{"time":0,"angle":10.93,"curve":[0.319,0.57,0.641,1]},{"time":0.2333,"angle":2.79,"curve":[0.402,0.01,0.653,1]},{"time":0.9,"angle":21.45,"curve":[0.401,0.01,0.697,0.59]},{"time":1.3333,"angle":10.93}]},"feelers8":{"rotate":[{"time":0,"angle":16.32,"curve":[0.344,0.4,0.637,1]},{"time":0.4667,"angle":7.28,"curve":[0.374,0.01,0.653,1]},{"time":1.1,"angle":28.2,"curve":[0.374,0.01,0.699,0.44]},{"time":1.3333,"angle":16.32}]},"left_lips":{"rotate":[{"time":0,"angle":0,"curve":[0.25,0,0.75,1]},{"time":0.1667,"angle":-12.09,"curve":[0.25,0,0.75,1]},{"time":0.3667,"angle":0,"curve":[0.25,0,0.75,1]},{"time":0.5,"angle":-12.09,"curve":[0.25,0,0.75,1]},{"time":0.6667,"angle":0}]},"right_lips":{"rotate":[{"time":0,"angle":0},{"time":0.1667,"angle":10.24},{"time":0.3667,"angle":0},{"time":0.5,"angle":10.24},{"time":0.6667,"angle":0}]},"body_4":{"rotate":[{"time":0,"angle":-17.77,"curve":[0.25,0,0.75,1]},{"time":0.6667,"angle":33.77,"curve":[0.25,0,0.75,1]},{"time":1.3333,"angle":-17.77}],"translate":[{"time":0,"x":2.4,"y":-4.82,"curve":[0.306,0.48,0.608,0.99]},{"time":0.3667,"x":-61.61,"y":-39.59,"curve":[0.383,0,0.643,1]},{"time":1.0333,"x":28.27,"y":5.96,"curve":[0.381,0,0.702,0.62]},{"time":1.3333,"x":2.4,"y":-4.82}]},"leg4":{"translate":[{"time":0,"x":27.57,"y":0}]},"right_leg_1":{"rotate":[{"time":0,"angle":-0.1}]},"right_leg_2":{"rotate":[{"time":0,"angle":0.34}]},"leg1":{"translate":[{"time":0,"x":-28.99,"y":0}]}}}}}